{
  "placeholderImages": [
    { "id": "hero", "description": "Construction worker on a building frame", "imageUrl": "https://picsum.photos/seed/1/1280/720", "imageHint": "construction site" },
    { "id": "whyus", "description": "Construction workers planning on a site", "imageUrl": "https://picsum.photos/seed/99/600/450", "imageHint": "construction planning" },
    { "id": "about-us", "description": "A modern building under construction", "imageUrl": "https://picsum.photos/seed/101/800/600", "imageHint": "building construction" },
    { "id": "solar1", "description": "Solar panels on a commercial building", "imageUrl": "https://picsum.photos/seed/2/600/400", "imageHint": "commercial solar" },
    { "id": "solar2", "description": "Array of solar panels in a field", "imageUrl": "https://picsum.photos/seed/3/600/400", "imageHint": "solar farm" },
    { "id": "solar3", "description": "Worker cleaning solar panels", "imageUrl": "https://picsum.photos/seed/4/600/400", "imageHint": "solar maintenance" },
    { "id": "contracting1", "description": "Heavy machinery at a construction site", "imageUrl": "https://picsum.photos/seed/5/600/400", "imageHint": "construction machinery" },
    { "id": "contracting2", "description": "Architect and builder looking at blueprints on site", "imageUrl": "https://picsum.photos/seed/6/600/400", "imageHint": "construction blueprints" },
    { "id": "contracting3", "description": "A newly constructed home exterior", "imageUrl": "https://picsum.photos/seed/7/600/400", "imageHint": "new house" },
    { "id": "repair1", "description": "Electrician working on a fuse box", "imageUrl": "https://picsum.photos/seed/8/600/400", "imageHint": "electrician fuse" },
    { "id": "repair2", "description": "Close up of electrical wiring", "imageUrl": "https://picsum.photos/seed/9/600/400", "imageHint": "electrical wiring" },
    { "id": "repair3", "description": "Utility worker on a power line", "imageUrl": "https://picsum.photos/seed/10/600/400", "imageHint": "utility worker" },
    { "id": "construction1", "description": "Pouring concrete for a foundation", "imageUrl": "https://picsum.photos/seed/11/600/400", "imageHint": "concrete pour" },
    { "id": "construction2", "description": "Welder working on a steel frame", "imageUrl": "https://picsum.photos/seed/12/600/400", "imageHint": "welder steel" },
    { "id": "construction3", "description": "Interior framing of a house under construction", "imageUrl": "https://picsum.photos/seed/13/600/400", "imageHint": "house framing" },
    { "id": "consultation1", "description": "Engineers meeting at a construction site", "imageUrl": "https://picsum.photos/seed/14/600/400", "imageHint": "construction meeting" },
    { "id": "consultation2", "description": "Safety inspector on site", "imageUrl": "https://picsum.photos/seed/15/600/400", "imageHint": "safety inspector" },
    { "id": "consultation3", "description": "Handshake in front of a construction project", "imageUrl": "https://picsum.photos/seed/16/600/400", "imageHint": "construction deal" },
    { "id": "team1", "description": "Portrait of a construction manager", "imageUrl": "https://picsum.photos/seed/20/400/400", "imageHint": "construction manager" },
    { "id": "team2", "description": "Portrait of a female architect", "imageUrl": "https://picsum.photos/seed/21/400/400", "imageHint": "female architect" },
    { "id": "team3", "description": "Portrait of an operations manager", "imageUrl": "https://picsum.photos/seed/22/400/400", "imageHint": "operations manager" },
    { "id": "team4", "description": "Portrait of a female electrician", "imageUrl": "https://picsum.photos/seed/23/400/400", "imageHint": "female electrician" }
  ]
}
